README.md
setup.py
pickpocket/__init__.py
pickpocket/base.py
pickpocket/compare.py
pickpocket/model.py
pickpocket/optimizer.py
pickpocket/pickPocket.py
pickpocket/utils.py
pickpocket.egg-info/PKG-INFO
pickpocket.egg-info/SOURCES.txt
pickpocket.egg-info/dependency_links.txt
pickpocket.egg-info/entry_points.txt
pickpocket.egg-info/requires.txt
pickpocket.egg-info/top_level.txt