Metadata-Version: 1.0
Name: pickpocket
Version: 0.1.3
Summary: Pick ligand specific pockets
Home-page: https://github.com/benjaminviart/PickPocket
Author: Benjamin Viart and Claudio Lorenzi
Author-email: claudio.lorenzi@gmail.com
License: UNKNOWN
Platform: UNKNOWN
